{
  "version": "7",
  "dialect": "sqlite",
  "entries": [
    {
      "idx": 0,
      "version": "6",
      "when": 1780837324230,
      "tag": "0000_careful_vulcan",
      "breakpoints": true
    },
    {
      "idx": 1,
      "version": "6",
      "when": 1780840000000,
      "tag": "0001_keyword_top_results",
      "breakpoints": true
    },
    {
      "idx": 2,
      "version": "6",
      "when": 1780921007546,
      "tag": "0001_overconfident_giant_girl",
      "breakpoints": true
    },
    {
      "idx": 3,
      "version": "6",
      "when": 1780929314141,
      "tag": "0002_deep_black_tarantula",
      "breakpoints": true
    },
    {
      "idx": 4,
      "version": "6",
      "when": 1781096196545,
      "tag": "0004_bent_squadron_sinister",
      "breakpoints": true
    },
    {
      "idx": 5,
      "version": "6",
      "when": 1781096673533,
      "tag": "0005_mysterious_nicolaos",
      "breakpoints": true
    },
    {
      "idx": 6,
      "version": "6",
      "when": 1781097551376,
      "tag": "0006_rainy_sinister_six",
      "breakpoints": true
    },
    {
      "idx": 7,
      "version": "6",
      "when": 1781099215904,
      "tag": "0007_white_victor_mancha",
      "breakpoints": true
    },
    {
      "idx": 8,
      "version": "6",
      "when": 1781245366492,
      "tag": "0008_outgoing_scarecrow",
      "breakpoints": true
    },
    {
      "idx": 9,
      "version": "6",
      "when": 1781271030011,
      "tag": "0009_shallow_ultragirl",
      "breakpoints": true
    },
    {
      "idx": 10,
      "version": "6",
      "when": 1781273835553,
      "tag": "0010_fluffy_dust",
      "breakpoints": true
    },
    {
      "idx": 11,
      "version": "6",
      "when": 1781298298587,
      "tag": "0011_fair_archangel",
      "breakpoints": true
    },
    {
      "idx": 12,
      "version": "6",
      "when": 1781616171641,
      "tag": "0012_wandering_corsair",
      "breakpoints": true
    }
  ]
}